Conceal_Pass.py
conceal_pass-1.0.0.dist-info/METADATA
conceal_pass-1.0.0.dist-info/WHEEL
conceal_pass-1.0.0.dist-info/licenses/LICENSE
conceal_pass-1.0.0.dist-info/RECORD
